{
	"Routes": [
		{
			"DownstreamPathTemplate": "/api/user/authetication", // Url da API.
			"DownstreamScheme": "https",
			"DownstreamHostAndPorts": [
				{
					"Host": "localhost",
					"Port": 7125
				}
			],
			"UpstreamPathTemplate": "/gateway/user/authetication", // Url do Gateway
			"UpstreamHttpMethod": [ "GET" ], // Methos aceitos.
			"RouteIsCaseSensitive": false,
			"DownstreamHttpMethod": "GET", // Method da API.
			"RateLimitOptions": {
				"ClientWhitelist": [],
				"EnableRateLimiting": true,
				"Period": "1m",
				"PeriodTimespan": 60,
				"Limit": 10
			}
		},
		{
			"DownstreamPathTemplate": "/api/user/get/{userId}", // Url da API.
			"DownstreamScheme": "https",
			"DownstreamHostAndPorts": [
				{
					"Host": "localhost",
					"Port": 7125
				}
			],
			"UpstreamPathTemplate": "/gateway/user/get/{userId}", // Url do Gateway
			"UpstreamHttpMethod": [ "GET" ], // Methos aceitos.
			"RouteIsCaseSensitive": false,
			"DownstreamHttpMethod": "GET", // Method da API.
			"RateLimitOptions": {
				"ClientWhitelist": [],
				"EnableRateLimiting": true,
				"Period": "1m",
				"PeriodTimespan": 60,
				"Limit": 10
			}
		}
	],
	"GlobalConfiguration": {
		"BaseUrl": "https://localhost:7282",
		"RateLimitOptions": {
			"DisableRateLimitHeaders": false,
			"QuotaExceededMessage": "Limite de requisições para a API atingido!",
			"HttpStatusCode": 429,
			"ClientIdHeader": "TOOLS.USER.API"
		}
	}
}